{
    "savingData": {
        "roomID": 1,
        "roomsCleared": 0,
        "spacesMoved": 15,
        "specialSpacesMoved": 288,
        "deaths": 1,
        "seconds": 10.083325386047364,
        "minutes": 0.0,
        "hours": 0.0
    },
    "predictingStats": {
        "challengeSkillBalance": 5,
        "actionAwarenessMerging": 5,
        "clearGoals": 5,
        "unambiguousFeedback": 5,
        "totalConcentration": 4,
        "lossOfSelfConsciousness": 5,
        "transformationOfTime": 5
    }
}